ibutsu_client/__init__.py
ibutsu_client/api_client.py
ibutsu_client/api_response.py
ibutsu_client/configuration.py
ibutsu_client/exceptions.py
ibutsu_client/py.typed
ibutsu_client/rest.py
ibutsu_client/api/__init__.py
ibutsu_client/api/admin_project_management_api.py
ibutsu_client/api/admin_user_management_api.py
ibutsu_client/api/artifact_api.py
ibutsu_client/api/dashboard_api.py
ibutsu_client/api/group_api.py
ibutsu_client/api/health_api.py
ibutsu_client/api/import_api.py
ibutsu_client/api/login_api.py
ibutsu_client/api/project_api.py
ibutsu_client/api/result_api.py
ibutsu_client/api/run_api.py
ibutsu_client/api/task_api.py
ibutsu_client/api/user_api.py
ibutsu_client/api/widget_api.py
ibutsu_client/api/widget_config_api.py
ibutsu_client/models/__init__.py
ibutsu_client/models/account_recovery.py
ibutsu_client/models/account_registration.py
ibutsu_client/models/account_reset.py
ibutsu_client/models/artifact.py
ibutsu_client/models/artifact_list.py
ibutsu_client/models/create_token.py
ibutsu_client/models/credentials.py
ibutsu_client/models/dashboard.py
ibutsu_client/models/dashboard_list.py
ibutsu_client/models/group.py
ibutsu_client/models/group_list.py
ibutsu_client/models/health.py
ibutsu_client/models/health_info.py
ibutsu_client/models/login_config.py
ibutsu_client/models/login_error.py
ibutsu_client/models/login_support.py
ibutsu_client/models/login_token.py
ibutsu_client/models/model_import.py
ibutsu_client/models/pagination.py
ibutsu_client/models/project.py
ibutsu_client/models/project_list.py
ibutsu_client/models/result.py
ibutsu_client/models/result_list.py
ibutsu_client/models/run.py
ibutsu_client/models/run_list.py
ibutsu_client/models/token.py
ibutsu_client/models/token_list.py
ibutsu_client/models/update_run.py
ibutsu_client/models/user.py
ibutsu_client/models/user_list.py
ibutsu_client/models/widget_config.py
ibutsu_client/models/widget_config_list.py
ibutsu_client/models/widget_param.py
ibutsu_client/models/widget_type.py
ibutsu_client-3.1.1.dist-info/METADATA
ibutsu_client-3.1.1.dist-info/WHEEL
ibutsu_client-3.1.1.dist-info/licenses/LICENSE
ibutsu_client-3.1.1.dist-info/RECORD
