Metadata-Version: 2.4
Name: ibutsu-client
Version: 3.1.1
Summary: A system to store and query test results
Project-URL: Source, https://github.com/ibutsu/ibutsu-client-python
Project-URL: Tracker, https://github.com/ibutsu/ibutsu-client-python/issues
Author: Raoul Snyman
Maintainer-email: Mike Shriver <mshriver@redhat.com>
License-Expression: MIT
License-File: LICENSE
Keywords: Ibutsu API,OpenAPI,OpenAPI-Generator,results,testing
Classifier: Development Status :: 4 - Beta
Classifier: Intended Audience :: Developers
Classifier: License :: OSI Approved :: MIT License
Classifier: Operating System :: OS Independent
Classifier: Programming Language :: Python
Classifier: Programming Language :: Python :: 3.11
Classifier: Programming Language :: Python :: 3.12
Classifier: Programming Language :: Python :: 3.13
Classifier: Programming Language :: Python :: Implementation :: CPython
Classifier: Programming Language :: Python :: Implementation :: PyPy
Classifier: Topic :: Software Development :: Libraries :: Python Modules
Classifier: Topic :: Software Development :: Testing
Requires-Python: >=3.11
Requires-Dist: lazy-imports<2,>=1
Requires-Dist: pydantic>=2
Requires-Dist: python-dateutil>=2.8.2
Requires-Dist: typing-extensions>=4.7.1
Requires-Dist: urllib3<3.0.0,>=2.1.0
